confpy/__init__.py
confpy/__init__.pyc
confpy/api.py
confpy/cmd.py
confpy/example.py
confpy/example.pyc
confpy/exc.py
confpy/exc.pyc
confpy/parser.py
confpy/parser.pyc
confpy/__pycache__/__init__.cpython-34.pyc
confpy/__pycache__/__init__.cpython-35.pyc
confpy/__pycache__/__init__.cpython-36.pyc
confpy/__pycache__/__init__.cpython-37.pyc
confpy/__pycache__/example.cpython-34.pyc
confpy/__pycache__/example.cpython-35.pyc
confpy/__pycache__/example.cpython-36.pyc
confpy/__pycache__/example.cpython-37.pyc
confpy/__pycache__/exc.cpython-34.pyc
confpy/__pycache__/exc.cpython-35.pyc
confpy/__pycache__/exc.cpython-36.pyc
confpy/__pycache__/exc.cpython-37.pyc
confpy/__pycache__/parser.cpython-34.pyc
confpy/__pycache__/parser.cpython-35.pyc
confpy/__pycache__/parser.cpython-36.pyc
confpy/__pycache__/parser.cpython-37.pyc
confpy/core/__init__.py
confpy/core/__init__.pyc
confpy/core/compat.py
confpy/core/compat.pyc
confpy/core/config.py
confpy/core/config.pyc
confpy/core/namespace.py
confpy/core/namespace.pyc
confpy/core/option.py
confpy/core/option.pyc
confpy/core/__pycache__/__init__.cpython-34.pyc
confpy/core/__pycache__/__init__.cpython-35.pyc
confpy/core/__pycache__/__init__.cpython-36.pyc
confpy/core/__pycache__/__init__.cpython-37.pyc
confpy/core/__pycache__/compat.cpython-34.pyc
confpy/core/__pycache__/compat.cpython-35.pyc
confpy/core/__pycache__/compat.cpython-36.pyc
confpy/core/__pycache__/compat.cpython-37.pyc
confpy/core/__pycache__/config.cpython-34.pyc
confpy/core/__pycache__/config.cpython-35.pyc
confpy/core/__pycache__/config.cpython-36.pyc
confpy/core/__pycache__/config.cpython-37.pyc
confpy/core/__pycache__/namespace.cpython-34.pyc
confpy/core/__pycache__/namespace.cpython-35.pyc
confpy/core/__pycache__/namespace.cpython-36.pyc
confpy/core/__pycache__/namespace.cpython-37.pyc
confpy/core/__pycache__/option.cpython-34.pyc
confpy/core/__pycache__/option.cpython-35.pyc
confpy/core/__pycache__/option.cpython-36.pyc
confpy/core/__pycache__/option.cpython-37.pyc
confpy-0.11.0.dist-info/LICENSE
confpy-0.11.0.dist-info/METADATA
confpy-0.11.0.dist-info/WHEEL
confpy-0.11.0.dist-info/entry_points.txt
confpy-0.11.0.dist-info/top_level.txt
confpy-0.11.0.dist-info/RECORD
