Metadata-Version: 2.1
Name: confpy
Version: 0.11.0
Summary: Config file parsing and option management.
Home-page: https://github.com/kevinconway/confpy
Author: Kevin Conway
Author-email: kevinjacobconway@gmail.com
License: MIT
Platform: UNKNOWN
Provides-Extra: generator
Requires-Dist: Jinja2 ; extra == 'generator'
